<?xml version="1.0" encoding="utf-8"?>
<TextureAtlas imagePath="accordboy.png">
	<!-- Created with Adobe Animate version 20.0.0.17400 -->
	<!-- http://www.adobe.com/products/animate.html -->
	<SubTexture name="leedown0000" x="1135" y="0" width="463" height="408" frameX="0" frameY="-4" frameWidth="463" frameHeight="412"/>
	<SubTexture name="leedown0001" x="1135" y="0" width="463" height="408" frameX="0" frameY="-4" frameWidth="463" frameHeight="412"/>
	<SubTexture name="leedown0002" x="1608" y="0" width="448" height="409" frameX="-8" frameY="0" frameWidth="463" frameHeight="412"/>
	<SubTexture name="leedown0003" x="1608" y="0" width="448" height="409" frameX="-8" frameY="0" frameWidth="463" frameHeight="412"/>
	<SubTexture name="leedown0004" x="1608" y="0" width="448" height="409" frameX="-8" frameY="0" frameWidth="463" frameHeight="412"/>
	<SubTexture name="leedown0005" x="1608" y="0" width="448" height="409" frameX="-8" frameY="0" frameWidth="463" frameHeight="412"/>
	<SubTexture name="leedown0006" x="1608" y="0" width="448" height="409" frameX="-8" frameY="0" frameWidth="463" frameHeight="412"/>
	<SubTexture name="leedown0007" x="1608" y="0" width="448" height="409" frameX="-8" frameY="0" frameWidth="463" frameHeight="412"/>
	<SubTexture name="leedown0008" x="1608" y="0" width="448" height="409" frameX="-8" frameY="0" frameWidth="463" frameHeight="412"/>
	<SubTexture name="leedown0009" x="1608" y="0" width="448" height="409" frameX="-8" frameY="0" frameWidth="463" frameHeight="412"/>
	<SubTexture name="leedown0010" x="1608" y="0" width="448" height="409" frameX="-8" frameY="0" frameWidth="463" frameHeight="412"/>
	<SubTexture name="leedown0011" x="1608" y="0" width="448" height="409" frameX="-8" frameY="0" frameWidth="463" frameHeight="412"/>
	<SubTexture name="leedown0012" x="1608" y="0" width="448" height="409" frameX="-8" frameY="0" frameWidth="463" frameHeight="412"/>
	<SubTexture name="leedown0013" x="1608" y="0" width="448" height="409" frameX="-8" frameY="0" frameWidth="463" frameHeight="412"/>
	<SubTexture name="leedown0014" x="1608" y="0" width="448" height="409" frameX="-8" frameY="0" frameWidth="463" frameHeight="412"/>
	<SubTexture name="leedown0015" x="1608" y="0" width="448" height="409" frameX="-8" frameY="0" frameWidth="463" frameHeight="412"/>
	<SubTexture name="leedown0016" x="1608" y="0" width="448" height="409" frameX="-8" frameY="0" frameWidth="463" frameHeight="412"/>
	<SubTexture name="leedown0017" x="1608" y="0" width="448" height="409" frameX="-8" frameY="0" frameWidth="463" frameHeight="412"/>
	<SubTexture name="leedown0018" x="1608" y="0" width="448" height="409" frameX="-8" frameY="0" frameWidth="463" frameHeight="412"/>
	<SubTexture name="leedown0019" x="1608" y="0" width="448" height="409" frameX="-8" frameY="0" frameWidth="463" frameHeight="412"/>
	<SubTexture name="leedown0020" x="1608" y="0" width="448" height="409" frameX="-8" frameY="0" frameWidth="463" frameHeight="412"/>
	<SubTexture name="leedown0021" x="1608" y="0" width="448" height="409" frameX="-8" frameY="0" frameWidth="463" frameHeight="412"/>
	<SubTexture name="leedown0022" x="1608" y="0" width="448" height="409" frameX="-8" frameY="0" frameWidth="463" frameHeight="412"/>
	<SubTexture name="leedown0023" x="1608" y="0" width="448" height="409" frameX="-8" frameY="0" frameWidth="463" frameHeight="412"/>
	<SubTexture name="leedown0024" x="1608" y="0" width="448" height="409" frameX="-8" frameY="0" frameWidth="463" frameHeight="412"/>
	<SubTexture name="leeleft0000" x="0" y="0" width="556" height="527" frameX="0" frameY="-2" frameWidth="564" frameHeight="531"/>
	<SubTexture name="leeleft0001" x="0" y="0" width="556" height="527" frameX="0" frameY="-2" frameWidth="564" frameHeight="531"/>
	<SubTexture name="leeleft0002" x="566" y="0" width="559" height="531" frameX="-5" frameY="0" frameWidth="564" frameHeight="531"/>
	<SubTexture name="leeleft0003" x="566" y="0" width="559" height="531" frameX="-5" frameY="0" frameWidth="564" frameHeight="531"/>
	<SubTexture name="leeleft0004" x="566" y="0" width="559" height="531" frameX="-5" frameY="0" frameWidth="564" frameHeight="531"/>
	<SubTexture name="leeleft0005" x="566" y="0" width="559" height="531" frameX="-5" frameY="0" frameWidth="564" frameHeight="531"/>
	<SubTexture name="leeleft0006" x="566" y="0" width="559" height="531" frameX="-5" frameY="0" frameWidth="564" frameHeight="531"/>
	<SubTexture name="leeleft0007" x="566" y="0" width="559" height="531" frameX="-5" frameY="0" frameWidth="564" frameHeight="531"/>
	<SubTexture name="leeleft0008" x="566" y="0" width="559" height="531" frameX="-5" frameY="0" frameWidth="564" frameHeight="531"/>
	<SubTexture name="leeleft0009" x="566" y="0" width="559" height="531" frameX="-5" frameY="0" frameWidth="564" frameHeight="531"/>
	<SubTexture name="leeleft0010" x="566" y="0" width="559" height="531" frameX="-5" frameY="0" frameWidth="564" frameHeight="531"/>
	<SubTexture name="leeleft0011" x="566" y="0" width="559" height="531" frameX="-5" frameY="0" frameWidth="564" frameHeight="531"/>
	<SubTexture name="leeleft0012" x="566" y="0" width="559" height="531" frameX="-5" frameY="0" frameWidth="564" frameHeight="531"/>
	<SubTexture name="leeleft0013" x="566" y="0" width="559" height="531" frameX="-5" frameY="0" frameWidth="564" frameHeight="531"/>
	<SubTexture name="leeleft0014" x="566" y="0" width="559" height="531" frameX="-5" frameY="0" frameWidth="564" frameHeight="531"/>
	<SubTexture name="leeup0000" x="2066" y="0" width="399" height="571" frameX="-1" frameY="0" frameWidth="406" frameHeight="571"/>
	<SubTexture name="leeup0001" x="2066" y="0" width="399" height="571" frameX="-1" frameY="0" frameWidth="406" frameHeight="571"/>
	<SubTexture name="leeup0002" x="2475" y="0" width="406" height="566" frameX="0" frameY="-5" frameWidth="406" frameHeight="571"/>
	<SubTexture name="leeup0003" x="2475" y="0" width="406" height="566" frameX="0" frameY="-5" frameWidth="406" frameHeight="571"/>
	<SubTexture name="leeup0004" x="2475" y="0" width="406" height="566" frameX="0" frameY="-5" frameWidth="406" frameHeight="571"/>
	<SubTexture name="leeidle0000" x="2891" y="0" width="381" height="549" frameX="-50" frameY="0" frameWidth="492" frameHeight="549"/>
	<SubTexture name="leeidle0001" x="2891" y="0" width="381" height="549" frameX="-50" frameY="0" frameWidth="492" frameHeight="549"/>
	<SubTexture name="leeidle0002" x="3282" y="0" width="379" height="541" frameX="-55" frameY="-8" frameWidth="492" frameHeight="549"/>
	<SubTexture name="leeidle0003" x="3282" y="0" width="379" height="541" frameX="-55" frameY="-8" frameWidth="492" frameHeight="549"/>
	<SubTexture name="leeidle0004" x="3671" y="0" width="357" height="484" frameX="-79" frameY="-61" frameWidth="492" frameHeight="549"/>
	<SubTexture name="leeidle0005" x="3671" y="0" width="357" height="484" frameX="-79" frameY="-61" frameWidth="492" frameHeight="549"/>
	<SubTexture name="leeidle0006" x="0" y="581" width="354" height="494" frameX="-78" frameY="-52" frameWidth="492" frameHeight="549"/>
	<SubTexture name="leeidle0007" x="0" y="581" width="354" height="494" frameX="-78" frameY="-52" frameWidth="492" frameHeight="549"/>
	<SubTexture name="leeidle0008" x="364" y="581" width="492" height="532" frameX="0" frameY="-16" frameWidth="492" frameHeight="549"/>
	<SubTexture name="leeidle0009" x="364" y="581" width="492" height="532" frameX="0" frameY="-16" frameWidth="492" frameHeight="549"/>
	<SubTexture name="leeidle0010" x="866" y="581" width="481" height="524" frameX="-7" frameY="-20" frameWidth="492" frameHeight="549"/>
	<SubTexture name="leeidle0011" x="866" y="581" width="481" height="524" frameX="-7" frameY="-20" frameWidth="492" frameHeight="549"/>
	<SubTexture name="leeidle0012" x="3671" y="0" width="357" height="484" frameX="-79" frameY="-61" frameWidth="492" frameHeight="549"/>
	<SubTexture name="leeidle0013" x="3671" y="0" width="357" height="484" frameX="-79" frameY="-61" frameWidth="492" frameHeight="549"/>
	<SubTexture name="leeidle0014" x="0" y="581" width="354" height="494" frameX="-78" frameY="-52" frameWidth="492" frameHeight="549"/>
	<SubTexture name="leeidle0015" x="0" y="581" width="354" height="494" frameX="-78" frameY="-52" frameWidth="492" frameHeight="549"/>
	<SubTexture name="leeright0000" x="1357" y="581" width="442" height="524" frameX="0" frameY="-9" frameWidth="442" frameHeight="533"/>
	<SubTexture name="leeright0001" x="1357" y="581" width="442" height="524" frameX="0" frameY="-9" frameWidth="442" frameHeight="533"/>
	<SubTexture name="leeright0002" x="1809" y="581" width="437" height="533" frameX="0" frameY="0" frameWidth="442" frameHeight="533"/>
	<SubTexture name="leeright0003" x="1809" y="581" width="437" height="533" frameX="0" frameY="0" frameWidth="442" frameHeight="533"/>
	<SubTexture name="leeright0004" x="1809" y="581" width="437" height="533" frameX="0" frameY="0" frameWidth="442" frameHeight="533"/>
	<SubTexture name="leeright0005" x="1809" y="581" width="437" height="533" frameX="0" frameY="0" frameWidth="442" frameHeight="533"/>
	<SubTexture name="leeright0006" x="1809" y="581" width="437" height="533" frameX="0" frameY="0" frameWidth="442" frameHeight="533"/>
	<SubTexture name="leeright0007" x="1809" y="581" width="437" height="533" frameX="0" frameY="0" frameWidth="442" frameHeight="533"/>
	<SubTexture name="leeright0008" x="1809" y="581" width="437" height="533" frameX="0" frameY="0" frameWidth="442" frameHeight="533"/>
	<SubTexture name="leeright0009" x="1809" y="581" width="437" height="533" frameX="0" frameY="0" frameWidth="442" frameHeight="533"/>
	<SubTexture name="leeright0010" x="1809" y="581" width="437" height="533" frameX="0" frameY="0" frameWidth="442" frameHeight="533"/>
	<SubTexture name="leeright0011" x="1809" y="581" width="437" height="533" frameX="0" frameY="0" frameWidth="442" frameHeight="533"/>
	<SubTexture name="leeright0012" x="1809" y="581" width="437" height="533" frameX="0" frameY="0" frameWidth="442" frameHeight="533"/>
	<SubTexture name="leeright0013" x="1809" y="581" width="437" height="533" frameX="0" frameY="0" frameWidth="442" frameHeight="533"/>
	<SubTexture name="leeright0014" x="1809" y="581" width="437" height="533" frameX="0" frameY="0" frameWidth="442" frameHeight="533"/>
	<SubTexture name="leeright0015" x="1809" y="581" width="437" height="533" frameX="0" frameY="0" frameWidth="442" frameHeight="533"/>
	<SubTexture name="leeright0016" x="1809" y="581" width="437" height="533" frameX="0" frameY="0" frameWidth="442" frameHeight="533"/>
	<SubTexture name="leeright0017" x="1809" y="581" width="437" height="533" frameX="0" frameY="0" frameWidth="442" frameHeight="533"/>
	<SubTexture name="leeright0018" x="1809" y="581" width="437" height="533" frameX="0" frameY="0" frameWidth="442" frameHeight="533"/>
	<SubTexture name="leeright0019" x="1809" y="581" width="437" height="533" frameX="0" frameY="0" frameWidth="442" frameHeight="533"/>
	<SubTexture name="leeright0020" x="1809" y="581" width="437" height="533" frameX="0" frameY="0" frameWidth="442" frameHeight="533"/>
	<SubTexture name="leeright0021" x="1809" y="581" width="437" height="533" frameX="0" frameY="0" frameWidth="442" frameHeight="533"/>
	<SubTexture name="leeright0022" x="1809" y="581" width="437" height="533" frameX="0" frameY="0" frameWidth="442" frameHeight="533"/>
	<SubTexture name="leeright0023" x="1809" y="581" width="437" height="533" frameX="0" frameY="0" frameWidth="442" frameHeight="533"/>
	<SubTexture name="leeright0024" x="1809" y="581" width="437" height="533" frameX="0" frameY="0" frameWidth="442" frameHeight="533"/>
</TextureAtlas>
